pandas_lineage/__init__.py
pandas_lineage/convention/__init__.py
pandas_lineage/convention/error_handling.py
pandas_lineage/custom_types/__init__.py
pandas_lineage/custom_types/lineage.py
pandas_lineage/custom_types/pandas.py
pandas_lineage/decorators/__init__.py
pandas_lineage/decorators/_utils.py
pandas_lineage/decorators/input.py
pandas_lineage/decorators/output.py
pandas_lineage/io/__init__.py
pandas_lineage/io/parsers/__init__.py
pandas_lineage/io/parsers/readers.py
pandas_lineage/tests/__init__.py
pandas_lineage/tests/data/abc123_dataframe.csv
pandas_lineage/tests/data/abc123_dataframe.snappy.parquet
pandas_lineage/tests/data/null_abc123_dataframe.csv
pandas_lineage/tests/io/__init__.py
pandas_lineage/tests/io/parsers/__init__.py
pandas_lineage/tests/io/parsers/test_readers.py
pandas_lineage/tests/types/__init__.py
pandas_lineage/tests/types/test_lineage.py
pandas_lineage-0.0.2.dist-info/WHEEL
pandas_lineage-0.0.2.dist-info/METADATA
pandas_lineage-0.0.2.dist-info/RECORD
