Metadata-Version: 2.1
Name: pandas-lineage
Version: 0.0.2
Summary: A pandas extension built for OpenLineage
License: BSD 3-Clause License
Author: Gage Russell
Author-email: gage.russell.dev@gmail.com
Requires-Python: >=3.8,<4.0
Classifier: License :: Other/Proprietary License
Classifier: Programming Language :: Python :: 3
Classifier: Programming Language :: Python :: 3.8
Classifier: Programming Language :: Python :: 3.9
Classifier: Programming Language :: Python :: 3.10
Requires-Dist: openlineage-python (==0.13.1)
Requires-Dist: pandas (==1.4.4)
